LICENSE
MANIFEST.in
README.rst
setup.py
django_admin_tree/__init__.py
django_admin_tree/admin.py
django_admin_tree/models.py
django_admin_tree/tests.py
django_admin_tree/views.py
django_admin_tree.egg-info/PKG-INFO
django_admin_tree.egg-info/SOURCES.txt
django_admin_tree.egg-info/dependency_links.txt
django_admin_tree.egg-info/not-zip-safe
django_admin_tree.egg-info/requires.txt
django_admin_tree.egg-info/top_level.txt
django_admin_tree/static/css/tree_style.css
django_admin_tree/static/images/hide.png
django_admin_tree/static/js/admin_tree.js
django_admin_tree/templates/admin/django_admin_tree/category_tree.html
django_admin_tree/templates/admin/django_admin_tree/change_form.html
django_admin_tree/templates/admin/django_admin_tree/recursive_categories.html
django_admin_tree/templatetags/__init__.py
django_admin_tree/templatetags/verbose_names.py
tests/__init__.py
tests/asgi.py
tests/manage.py
tests/settings.py
tests/myapp/__init__.py
tests/myapp/admin.py
tests/myapp/apps.py
tests/myapp/models.py
tests/myapp/tests.py
tests/myapp/urls.py
tests/myapp/views.py
tests/myapp/migrations/0001_initial.py
tests/myapp/migrations/__init__.py